{
  "experiment": "135_analysis",
  "q4_mixed": {
    "q": 4,
    "label": "open on-peak: exact(S134,n<=12)+DMRG(S135,n>12)",
    "series": {
      "4": 24.18438158902081,
      "5": 28.002414382832796,
      "6": 32.55585298012064,
      "7": 37.70329612803483,
      "8": 43.35590139818713,
      "9": 49.5185059389157,
      "10": 56.08226695228425,
      "11": 63.1422202382578,
      "12": 70.52283221016069,
      "14": 86.56432104508266,
      "16": 104.12978228282327,
      "18": 123.15948899476058,
      "20": 143.60095181531474,
      "24": 188.57676183387886
    },
    "data_fits": {
      "sizes": [
        4.0,
        5.0,
        6.0,
        7.0,
        8.0,
        9.0,
        10.0,
        11.0,
        12.0,
        14.0,
        16.0,
        18.0,
        20.0,
        24.0
      ],
      "power": {
        "kappa": 1.1711385108961154,
        "ssr": 0.0712967165777721,
        "r2": 0.9862350052405569
      },
      "forced_null_log": {
        "null": 2.0,
        "sigma": -1.8433067722650192,
        "ssr": 0.005145858790395554,
        "r2": 0.9980434056832151
      },
      "free_power_log": {
        "kappa": 2.305957653735262,
        "sigma": -2.5101629261948393,
        "ssr": 4.225458888367054e-05,
        "r2": 0.9999918420619845
      }
    },
    "kappa_pairwise": [
      {
        "pair": [
          4,
          5
        ],
        "L_mid": 4.47213595499958,
        "inv_lnL": 0.667616401390668,
        "kappa": 0.6569031353433518
      },
      {
        "pair": [
          5,
          6
        ],
        "L_mid": 5.477225575051661,
        "inv_lnL": 0.5880282075904121,
        "kappa": 0.8263775045615046
      },
      {
        "pair": [
          6,
          7
        ],
        "L_mid": 6.48074069840786,
        "inv_lnL": 0.535092772838108,
        "kappa": 0.9522523916289815
      },
      {
        "pair": [
          7,
          8
        ],
        "L_mid": 7.483314773547883,
        "inv_lnL": 0.4968509967969383,
        "kappa": 1.0461607857478041
      },
      {
        "pair": [
          8,
          9
        ],
        "L_mid": 8.48528137423857,
        "inv_lnL": 0.46765399597295326,
        "kappa": 1.1283766682062037
      },
      {
        "pair": [
          9,
          10
        ],
        "L_mid": 9.486832980505138,
        "inv_lnL": 0.4444632432316208,
        "kappa": 1.1814028017593599
      },
      {
        "pair": [
          10,
          11
        ],
        "L_mid": 10.488088481701515,
        "inv_lnL": 0.4254884276413387,
        "kappa": 1.2440431970469552
      },
      {
        "pair": [
          11,
          12
        ],
        "L_mid": 11.489125293076057,
        "inv_lnL": 0.409600887299688,
        "kappa": 1.2704875626740373
      },
      {
        "pair": [
          12,
          14
        ],
        "L_mid": 12.96148139681572,
        "inv_lnL": 0.39032280633497385,
        "kappa": 1.329551158713047
      },
      {
        "pair": [
          14,
          16
        ],
        "L_mid": 14.966629547095765,
        "inv_lnL": 0.3695733203605263,
        "kappa": 1.3835719869556262
      },
      {
        "pair": [
          16,
          18
        ],
        "L_mid": 16.97056274847714,
        "inv_lnL": 0.3531721626904215,
        "kappa": 1.425011210457165
      },
      {
        "pair": [
          18,
          20
        ],
        "L_mid": 18.973665961010276,
        "inv_lnL": 0.33978332515255616,
        "kappa": 1.4574540561327236
      },
      {
        "pair": [
          20,
          24
        ],
        "L_mid": 21.908902300206645,
        "inv_lnL": 0.32395032259636697,
        "kappa": 1.494430327034562
      }
    ],
    "kappa_invlnL": {
      "K_inf": 2.298863013557606,
      "slope": -2.493152349406747,
      "r2": 0.998421465747671,
      "ssr": 0.001235772787615836
    },
    "kappa_surface": {
      "free3": {
        "K_inf": 2.519795245688361,
        "s_log": -3.409675638955696,
        "d_surf": 1.7518507105985597,
        "ssr": 0.0011956138221828948,
        "r2": 0.9984727634482752
      },
      "fixed_null": {
        "null": 2.0,
        "s_log": -1.2547718978261415,
        "d_surf": -2.3641492718581403,
        "ssr": 0.0014176041278561914,
        "max_resid": 0.02324928241932267
      },
      "surface_only": {
        "K_inf": 1.6976100350143177,
        "d_surf": -4.7629565908402585,
        "ssr": 0.0017512065573819528,
        "r2": 0.9977630681291633
      }
    }
  },
  "q4_dmrg_only": {
    "q": 4,
    "label": "open on-peak: DMRG-only (S135)",
    "series": {
      "8": 43.35590139818713,
      "10": 56.08226695228425,
      "12": 70.52283221016069,
      "14": 86.56432104508266,
      "16": 104.12978228282327,
      "18": 123.15948899476058,
      "20": 143.60095181531474,
      "24": 188.57676183387886
    },
    "data_fits": {
      "sizes": [
        8.0,
        10.0,
        12.0,
        14.0,
        16.0,
        18.0,
        20.0,
        24.0
      ],
      "power": {
        "kappa": 1.3413992867641953,
        "ssr": 0.003765682821259033,
        "r2": 0.9977838354378877
      },
      "forced_null_log": {
        "null": 2.0,
        "sigma": -1.7137183039046726,
        "ssr": 0.0004267393289770861,
        "r2": 0.9989653986116928
      },
      "free_power_log": {
        "kappa": 2.33474710851203,
        "sigma": -2.57946285170452,
        "ssr": 9.330143131497032e-07,
        "r2": 0.9999994509061557
      }
    },
    "kappa_pairwise": [
      {
        "pair": [
          8,
          10
        ],
        "L_mid": 8.94427190999916,
        "inv_lnL": 0.45640982283733733,
        "kappa": 1.15341373847598
      },
      {
        "pair": [
          10,
          12
        ],
        "L_mid": 10.954451150103322,
        "inv_lnL": 0.4177552897120582,
        "kappa": 1.2566635405065605
      },
      {
        "pair": [
          12,
          14
        ],
        "L_mid": 12.96148139681572,
        "inv_lnL": 0.39032280633497385,
        "kappa": 1.329551158713047
      },
      {
        "pair": [
          14,
          16
        ],
        "L_mid": 14.966629547095765,
        "inv_lnL": 0.3695733203605263,
        "kappa": 1.3835719869556262
      },
      {
        "pair": [
          16,
          18
        ],
        "L_mid": 16.97056274847714,
        "inv_lnL": 0.3531721626904215,
        "kappa": 1.425011210457165
      },
      {
        "pair": [
          18,
          20
        ],
        "L_mid": 18.973665961010276,
        "inv_lnL": 0.33978332515255616,
        "kappa": 1.4574540561327236
      },
      {
        "pair": [
          20,
          24
        ],
        "L_mid": 21.908902300206645,
        "inv_lnL": 0.32395032259636697,
        "kappa": 1.494430327034562
      }
    ],
    "kappa_invlnL": {
      "K_inf": 2.336257624537526,
      "slope": -2.585361200284769,
      "r2": 0.9994918436647423,
      "ssr": 4.399502996264681e-05
    },
    "kappa_surface": {
      "free3": {
        "K_inf": 1.8873418344106603,
        "s_log": -0.6734209520576973,
        "d_surf": -3.8190776323044417,
        "ssr": 1.3894915577766491e-06,
        "r2": 0.9999839509385839
      },
      "fixed_null": {
        "null": 2.0,
        "s_log": -1.1527935699917657,
        "d_surf": -2.862925006675009,
        "ssr": 4.066394265857295e-06,
        "max_resid": 0.00144777352946035
      },
      "surface_only": {
        "K_inf": 1.7291381641590597,
        "d_surf": -5.163017964697584,
        "ssr": 6.670293355593782e-06,
        "r2": 0.9999229560286799
      }
    }
  },
  "q3_control": {
    "q": 3,
    "label": "open on-peak CONTROL: DMRG (no marginal op)",
    "series": {
      "8": 13.458553878395453,
      "12": 19.598632629190075,
      "16": 26.637062805201506,
      "20": 34.363284352906255,
      "24": 42.678855857731605
    },
    "data_fits": {
      "sizes": [
        8.0,
        12.0,
        16.0,
        20.0,
        24.0
      ],
      "power": {
        "kappa": 1.0508763228136169,
        "ssr": 0.0022946744120215553,
        "r2": 0.9972466723024704
      },
      "forced_null_log": {
        "null": 1.4,
        "sigma": -0.9094774110119452,
        "ssr": 0.0008402154385394498,
        "r2": 0.9910640795561766
      },
      "free_power_log": {
        "kappa": 1.9371442605738025,
        "sigma": -2.295105361998066,
        "ssr": 9.140162910783011e-07,
        "r2": 0.9999989032926165
      }
    },
    "kappa_pairwise": [
      {
        "pair": [
          8,
          12
        ],
        "L_mid": 9.797958971132712,
        "inv_lnL": 0.4381786656282297,
        "kappa": 0.9269476275036913
      },
      {
        "pair": [
          12,
          16
        ],
        "L_mid": 13.856406460551018,
        "inv_lnL": 0.38040927446953,
        "kappa": 1.0666072513053437
      },
      {
        "pair": [
          16,
          20
        ],
        "L_mid": 17.88854381999832,
        "inv_lnL": 0.3467213425637008,
        "kappa": 1.1413509063409248
      },
      {
        "pair": [
          20,
          24
        ],
        "L_mid": 21.908902300206645,
        "inv_lnL": 0.32395032259636697,
        "kappa": 1.188641339826866
      }
    ],
    "kappa_invlnL": {
      "K_inf": 1.9371528111364873,
      "slope": -2.2998435648673645,
      "r2": 0.998990929959734,
      "ssr": 3.952337980459256e-05
    },
    "kappa_surface": {
      "free3": {
        "K_inf": 1.3279997351395276,
        "s_log": 0.3115149406029588,
        "d_surf": -5.26651302152365,
        "ssr": 1.0942411387540522e-07,
        "r2": 0.9999972062967403
      },
      "fixed_null": {
        "null": 1.4,
        "s_log": 0.0030964884490467795,
        "d_surf": -4.645278208796219,
        "ssr": 6.589527123932026e-07,
        "max_resid": 0.00067339641968861
      },
      "surface_only": {
        "K_inf": 1.400700816806627,
        "d_surf": -4.638749087486852,
        "ssr": 6.698724766060131e-07,
        "r2": 0.9999828975090115
      }
    }
  }
}